{
  "formatVersion": 1,
  "database": {
    "version": 1,
    "identityHash": "5247b9f0e5e45c098f26eb5c67c72bc4",
    "entities": [
      {
        "tableName": "tasks",
        "createSql": "CREATE TABLE IF NOT EXISTS `${TABLE_NAME}` (`id` TEXT NOT NULL, `title` TEXT NOT NULL, `description` TEXT NOT NULL, `project_id` TEXT NOT NULL, `section_id` TEXT, `parent_task_id` TEXT, `priority` INTEGER NOT NULL, `due_date_epoch_day` INTEGER, `due_time_minute_of_day` INTEGER, `due_timezone` TEXT, `recurrence_rule` TEXT, `is_completed` INTEGER NOT NULL, `completed_at_millis` INTEGER, `sort_order` INTEGER NOT NULL, `created_at_millis` INTEGER NOT NULL, `updated_at_millis` INTEGER NOT NULL, PRIMARY KEY(`id`), FOREIGN KEY(`project_id`) REFERENCES `projects`(`id`) ON UPDATE NO ACTION ON DELETE CASCADE , FOREIGN KEY(`section_id`) REFERENCES `sections`(`id`) ON UPDATE NO ACTION ON DELETE SET NULL , FOREIGN KEY(`parent_task_id`) REFERENCES `tasks`(`id`) ON UPDATE NO ACTION ON DELETE CASCADE )",
        "fields": [
          {
            "fieldPath": "id",
            "columnName": "id",
            "affinity": "TEXT",
            "notNull": true
          },
          {
            "fieldPath": "title",
            "columnName": "title",
            "affinity": "TEXT",
            "notNull": true
          },
          {
            "fieldPath": "description",
            "columnName": "description",
            "affinity": "TEXT",
            "notNull": true
          },
          {
            "fieldPath": "projectId",
            "columnName": "project_id",
            "affinity": "TEXT",
            "notNull": true
          },
          {
            "fieldPath": "sectionId",
            "columnName": "section_id",
            "affinity": "TEXT"
          },
          {
            "fieldPath": "parentTaskId",
            "columnName": "parent_task_id",
            "affinity": "TEXT"
          },
          {
            "fieldPath": "priority",
            "columnName": "priority",
            "affinity": "INTEGER",
            "notNull": true
          },
          {
            "fieldPath": "dueDateEpochDay",
            "columnName": "due_date_epoch_day",
            "affinity": "INTEGER"
          },
          {
            "fieldPath": "dueTimeMinuteOfDay",
            "columnName": "due_time_minute_of_day",
            "affinity": "INTEGER"
          },
          {
            "fieldPath": "dueTimezone",
            "columnName": "due_timezone",
            "affinity": "TEXT"
          },
          {
            "fieldPath": "recurrenceRule",
            "columnName": "recurrence_rule",
            "affinity": "TEXT"
          },
          {
            "fieldPath": "isCompleted",
            "columnName": "is_completed",
            "affinity": "INTEGER",
            "notNull": true
          },
          {
            "fieldPath": "completedAtMillis",
            "columnName": "completed_at_millis",
            "affinity": "INTEGER"
          },
          {
            "fieldPath": "sortOrder",
            "columnName": "sort_order",
            "affinity": "INTEGER",
            "notNull": true
          },
          {
            "fieldPath": "createdAtMillis",
            "columnName": "created_at_millis",
            "affinity": "INTEGER",
            "notNull": true
          },
          {
            "fieldPath": "updatedAtMillis",
            "columnName": "updated_at_millis",
            "affinity": "INTEGER",
            "notNull": true
          }
        ],
        "primaryKey": {
          "autoGenerate": false,
          "columnNames": [
            "id"
          ]
        },
        "indices": [
          {
            "name": "index_tasks_project_id",
            "unique": false,
            "columnNames": [
              "project_id"
            ],
            "orders": [],
            "createSql": "CREATE INDEX IF NOT EXISTS `index_tasks_project_id` ON `${TABLE_NAME}` (`project_id`)"
          },
          {
            "name": "index_tasks_section_id",
            "unique": false,
            "columnNames": [
              "section_id"
            ],
            "orders": [],
            "createSql": "CREATE INDEX IF NOT EXISTS `index_tasks_section_id` ON `${TABLE_NAME}` (`section_id`)"
          },
          {
            "name": "index_tasks_parent_task_id",
            "unique": false,
            "columnNames": [
              "parent_task_id"
            ],
            "orders": [],
            "createSql": "CREATE INDEX IF NOT EXISTS `index_tasks_parent_task_id` ON `${TABLE_NAME}` (`parent_task_id`)"
          },
          {
            "name": "index_tasks_due_date_epoch_day",
            "unique": false,
            "columnNames": [
              "due_date_epoch_day"
            ],
            "orders": [],
            "createSql": "CREATE INDEX IF NOT EXISTS `index_tasks_due_date_epoch_day` ON `${TABLE_NAME}` (`due_date_epoch_day`)"
          },
          {
            "name": "index_tasks_is_completed",
            "unique": false,
            "columnNames": [
              "is_completed"
            ],
            "orders": [],
            "createSql": "CREATE INDEX IF NOT EXISTS `index_tasks_is_completed` ON `${TABLE_NAME}` (`is_completed`)"
          },
          {
            "name": "index_tasks_priority",
            "unique": false,
            "columnNames": [
              "priority"
            ],
            "orders": [],
            "createSql": "CREATE INDEX IF NOT EXISTS `index_tasks_priority` ON `${TABLE_NAME}` (`priority`)"
          }
        ],
        "foreignKeys": [
          {
            "table": "projects",
            "onDelete": "CASCADE",
            "onUpdate": "NO ACTION",
            "columns": [
              "project_id"
            ],
            "referencedColumns": [
              "id"
            ]
          },
          {
            "table": "sections",
            "onDelete": "SET NULL",
            "onUpdate": "NO ACTION",
            "columns": [
              "section_id"
            ],
            "referencedColumns": [
              "id"
            ]
          },
          {
            "table": "tasks",
            "onDelete": "CASCADE",
            "onUpdate": "NO ACTION",
            "columns": [
              "parent_task_id"
            ],
            "referencedColumns": [
              "id"
            ]
          }
        ]
      },
      {
        "tableName": "projects",
        "createSql": "CREATE TABLE IF NOT EXISTS `${TABLE_NAME}` (`id` TEXT NOT NULL, `name` TEXT NOT NULL, `color` INTEGER NOT NULL, `icon_name` TEXT NOT NULL, `is_inbox` INTEGER NOT NULL, `is_archived` INTEGER NOT NULL, `default_view` TEXT NOT NULL, `sort_order` INTEGER NOT NULL, `created_at_millis` INTEGER NOT NULL, `updated_at_millis` INTEGER NOT NULL, PRIMARY KEY(`id`))",
        "fields": [
          {
            "fieldPath": "id",
            "columnName": "id",
            "affinity": "TEXT",
            "notNull": true
          },
          {
            "fieldPath": "name",
            "columnName": "name",
            "affinity": "TEXT",
            "notNull": true
          },
          {
            "fieldPath": "color",
            "columnName": "color",
            "affinity": "INTEGER",
            "notNull": true
          },
          {
            "fieldPath": "iconName",
            "columnName": "icon_name",
            "affinity": "TEXT",
            "notNull": true
          },
          {
            "fieldPath": "isInbox",
            "columnName": "is_inbox",
            "affinity": "INTEGER",
            "notNull": true
          },
          {
            "fieldPath": "isArchived",
            "columnName": "is_archived",
            "affinity": "INTEGER",
            "notNull": true
          },
          {
            "fieldPath": "defaultView",
            "columnName": "default_view",
            "affinity": "TEXT",
            "notNull": true
          },
          {
            "fieldPath": "sortOrder",
            "columnName": "sort_order",
            "affinity": "INTEGER",
            "notNull": true
          },
          {
            "fieldPath": "createdAtMillis",
            "columnName": "created_at_millis",
            "affinity": "INTEGER",
            "notNull": true
          },
          {
            "fieldPath": "updatedAtMillis",
            "columnName": "updated_at_millis",
            "affinity": "INTEGER",
            "notNull": true
          }
        ],
        "primaryKey": {
          "autoGenerate": false,
          "columnNames": [
            "id"
          ]
        },
        "indices": [
          {
            "name": "index_projects_sort_order",
            "unique": false,
            "columnNames": [
              "sort_order"
            ],
            "orders": [],
            "createSql": "CREATE INDEX IF NOT EXISTS `index_projects_sort_order` ON `${TABLE_NAME}` (`sort_order`)"
          }
        ]
      },
      {
        "tableName": "sections",
        "createSql": "CREATE TABLE IF NOT EXISTS `${TABLE_NAME}` (`id` TEXT NOT NULL, `name` TEXT NOT NULL, `project_id` TEXT NOT NULL, `sort_order` INTEGER NOT NULL, `is_collapsed` INTEGER NOT NULL, `created_at_millis` INTEGER NOT NULL, PRIMARY KEY(`id`), FOREIGN KEY(`project_id`) REFERENCES `projects`(`id`) ON UPDATE NO ACTION ON DELETE CASCADE )",
        "fields": [
          {
            "fieldPath": "id",
            "columnName": "id",
            "affinity": "TEXT",
            "notNull": true
          },
          {
            "fieldPath": "name",
            "columnName": "name",
            "affinity": "TEXT",
            "notNull": true
          },
          {
            "fieldPath": "projectId",
            "columnName": "project_id",
            "affinity": "TEXT",
            "notNull": true
          },
          {
            "fieldPath": "sortOrder",
            "columnName": "sort_order",
            "affinity": "INTEGER",
            "notNull": true
          },
          {
            "fieldPath": "isCollapsed",
            "columnName": "is_collapsed",
            "affinity": "INTEGER",
            "notNull": true
          },
          {
            "fieldPath": "createdAtMillis",
            "columnName": "created_at_millis",
            "affinity": "INTEGER",
            "notNull": true
          }
        ],
        "primaryKey": {
          "autoGenerate": false,
          "columnNames": [
            "id"
          ]
        },
        "indices": [
          {
            "name": "index_sections_project_id",
            "unique": false,
            "columnNames": [
              "project_id"
            ],
            "orders": [],
            "createSql": "CREATE INDEX IF NOT EXISTS `index_sections_project_id` ON `${TABLE_NAME}` (`project_id`)"
          }
        ],
        "foreignKeys": [
          {
            "table": "projects",
            "onDelete": "CASCADE",
            "onUpdate": "NO ACTION",
            "columns": [
              "project_id"
            ],
            "referencedColumns": [
              "id"
            ]
          }
        ]
      },
      {
        "tableName": "labels",
        "createSql": "CREATE TABLE IF NOT EXISTS `${TABLE_NAME}` (`id` TEXT NOT NULL, `name` TEXT NOT NULL, `color` INTEGER NOT NULL, `sort_order` INTEGER NOT NULL, PRIMARY KEY(`id`))",
        "fields": [
          {
            "fieldPath": "id",
            "columnName": "id",
            "affinity": "TEXT",
            "notNull": true
          },
          {
            "fieldPath": "name",
            "columnName": "name",
            "affinity": "TEXT",
            "notNull": true
          },
          {
            "fieldPath": "color",
            "columnName": "color",
            "affinity": "INTEGER",
            "notNull": true
          },
          {
            "fieldPath": "sortOrder",
            "columnName": "sort_order",
            "affinity": "INTEGER",
            "notNull": true
          }
        ],
        "primaryKey": {
          "autoGenerate": false,
          "columnNames": [
            "id"
          ]
        }
      },
      {
        "tableName": "task_label_cross_ref",
        "createSql": "CREATE TABLE IF NOT EXISTS `${TABLE_NAME}` (`task_id` TEXT NOT NULL, `label_id` TEXT NOT NULL, PRIMARY KEY(`task_id`, `label_id`), FOREIGN KEY(`task_id`) REFERENCES `tasks`(`id`) ON UPDATE NO ACTION ON DELETE CASCADE , FOREIGN KEY(`label_id`) REFERENCES `labels`(`id`) ON UPDATE NO ACTION ON DELETE CASCADE )",
        "fields": [
          {
            "fieldPath": "taskId",
            "columnName": "task_id",
            "affinity": "TEXT",
            "notNull": true
          },
          {
            "fieldPath": "labelId",
            "columnName": "label_id",
            "affinity": "TEXT",
            "notNull": true
          }
        ],
        "primaryKey": {
          "autoGenerate": false,
          "columnNames": [
            "task_id",
            "label_id"
          ]
        },
        "indices": [
          {
            "name": "index_task_label_cross_ref_label_id",
            "unique": false,
            "columnNames": [
              "label_id"
            ],
            "orders": [],
            "createSql": "CREATE INDEX IF NOT EXISTS `index_task_label_cross_ref_label_id` ON `${TABLE_NAME}` (`label_id`)"
          }
        ],
        "foreignKeys": [
          {
            "table": "tasks",
            "onDelete": "CASCADE",
            "onUpdate": "NO ACTION",
            "columns": [
              "task_id"
            ],
            "referencedColumns": [
              "id"
            ]
          },
          {
            "table": "labels",
            "onDelete": "CASCADE",
            "onUpdate": "NO ACTION",
            "columns": [
              "label_id"
            ],
            "referencedColumns": [
              "id"
            ]
          }
        ]
      },
      {
        "tableName": "filters",
        "createSql": "CREATE TABLE IF NOT EXISTS `${TABLE_NAME}` (`id` TEXT NOT NULL, `name` TEXT NOT NULL, `icon_name` TEXT NOT NULL, `color` INTEGER NOT NULL, `query` TEXT NOT NULL, `sort_order` INTEGER NOT NULL, PRIMARY KEY(`id`))",
        "fields": [
          {
            "fieldPath": "id",
            "columnName": "id",
            "affinity": "TEXT",
            "notNull": true
          },
          {
            "fieldPath": "name",
            "columnName": "name",
            "affinity": "TEXT",
            "notNull": true
          },
          {
            "fieldPath": "iconName",
            "columnName": "icon_name",
            "affinity": "TEXT",
            "notNull": true
          },
          {
            "fieldPath": "color",
            "columnName": "color",
            "affinity": "INTEGER",
            "notNull": true
          },
          {
            "fieldPath": "query",
            "columnName": "query",
            "affinity": "TEXT",
            "notNull": true
          },
          {
            "fieldPath": "sortOrder",
            "columnName": "sort_order",
            "affinity": "INTEGER",
            "notNull": true
          }
        ],
        "primaryKey": {
          "autoGenerate": false,
          "columnNames": [
            "id"
          ]
        }
      },
      {
        "tableName": "sync_metadata",
        "createSql": "CREATE TABLE IF NOT EXISTS `${TABLE_NAME}` (`id` TEXT NOT NULL, `last_sync_millis` INTEGER, `last_sync_status` TEXT, `pending_changes_count` INTEGER NOT NULL, `server_etag` TEXT, PRIMARY KEY(`id`))",
        "fields": [
          {
            "fieldPath": "id",
            "columnName": "id",
            "affinity": "TEXT",
            "notNull": true
          },
          {
            "fieldPath": "lastSyncMillis",
            "columnName": "last_sync_millis",
            "affinity": "INTEGER"
          },
          {
            "fieldPath": "lastSyncStatus",
            "columnName": "last_sync_status",
            "affinity": "TEXT"
          },
          {
            "fieldPath": "pendingChangesCount",
            "columnName": "pending_changes_count",
            "affinity": "INTEGER",
            "notNull": true
          },
          {
            "fieldPath": "serverEtag",
            "columnName": "server_etag",
            "affinity": "TEXT"
          }
        ],
        "primaryKey": {
          "autoGenerate": false,
          "columnNames": [
            "id"
          ]
        }
      }
    ],
    "setupQueries": [
      "CREATE TABLE IF NOT EXISTS room_master_table (id INTEGER PRIMARY KEY,identity_hash TEXT)",
      "INSERT OR REPLACE INTO room_master_table (id,identity_hash) VALUES(42, '5247b9f0e5e45c098f26eb5c67c72bc4')"
    ]
  }
}